[
  {
    "architecture": "sparcv9",
    "features": [
      "lite"
    ],
    "file_type": "tar.gz",
    "filename": "bellsoft-jdk13.0.1+10-solaris-sparcv9-lite.tar.gz",
    "image_type": "jdk",
    "java_version": "13.0.1+10",
    "jvm_impl": "hotspot",
    "md5": "aef67bab6eb93b72b38fa1673e42b88d",
    "md5_file": "bellsoft-jdk13.0.1+10-solaris-sparcv9-lite.tar.gz.md5",
    "os": "solaris",
    "release_type": "ga",
    "sha1": "860454c4cae2ab953b0703d8f65800683c5eb88d",
    "sha1_file": "bellsoft-jdk13.0.1+10-solaris-sparcv9-lite.tar.gz.sha1",
    "sha256": "8758cb04782619972dd45fb4e39acf62cd11228e125c4f9c0f2c9b66004fb135",
    "sha256_file": "bellsoft-jdk13.0.1+10-solaris-sparcv9-lite.tar.gz.sha256",
    "sha512": "726833b216aeda6b92d83c525569bcd2cb1cda4c8085fff7b8d9911cade4a3f8b01a91f6372d45017916a8b3ec527951eca70161755452071e73d745e5ea98b6",
    "sha512_file": "bellsoft-jdk13.0.1+10-solaris-sparcv9-lite.tar.gz.sha512",
    "size": 86273176,
    "url": "https://github.com/bell-sw/Liberica/releases/download/13.0.1+10/bellsoft-jdk13.0.1+10-solaris-sparcv9-lite.tar.gz",
    "vendor": "liberica",
    "version": "13.0.1+10"
  },
  {
    "architecture": "sparcv9",
    "features": [],
    "file_type": "tar.gz",
    "filename": "bellsoft-jdk13.0.1+10-solaris-sparcv9.tar.gz",
    "image_type": "jdk",
    "java_version": "13.0.1+10",
    "jvm_impl": "hotspot",
    "md5": "ca08e86b5cfde5f92bbb70a46d52ddde",
    "md5_file": "bellsoft-jdk13.0.1+10-solaris-sparcv9.tar.gz.md5",
    "os": "solaris",
    "release_type": "ga",
    "sha1": "1adf81d40cddfdb5be478455e8b475dd346e086f",
    "sha1_file": "bellsoft-jdk13.0.1+10-solaris-sparcv9.tar.gz.sha1",
    "sha256": "4ab693aced5362af4d318d812709fec15ca31d7c64b1d20b6ac1f286f3d4ae89",
    "sha256_file": "bellsoft-jdk13.0.1+10-solaris-sparcv9.tar.gz.sha256",
    "sha512": "9f24bb7d89d20346979145484c352524dff6e40100d979c8949eabf42b36c147c4c0491c8b07a9bb93779b35a0eb041456ace1c911105cf2cae206b81006ab21",
    "sha512_file": "bellsoft-jdk13.0.1+10-solaris-sparcv9.tar.gz.sha512",
    "size": 213760397,
    "url": "https://github.com/bell-sw/Liberica/releases/download/13.0.1+10/bellsoft-jdk13.0.1+10-solaris-sparcv9.tar.gz",
    "vendor": "liberica",
    "version": "13.0.1+10"
  }
]
