[
  {
    "architecture": "i686",
    "features": [],
    "file_type": "tar.gz",
    "filename": "zulu13.27.9-ca-jdk13-linux_i686.tar.gz",
    "image_type": "jdk",
    "java_version": "13",
    "jvm_impl": "hotspot",
    "md5": "51ea2aa32a871ed66931aedc0bc0065c",
    "md5_file": "zulu13.27.9-ca-jdk13-linux_i686.tar.gz.md5",
    "os": "linux",
    "release_type": "ga",
    "sha1": "68099c4724c531b0ad045a4ce68a2012f22bb9b3",
    "sha1_file": "zulu13.27.9-ca-jdk13-linux_i686.tar.gz.sha1",
    "sha256": "cf08df04c7e86e4f0547418ca8e162593e36784b11b811e9ccadd0801aa75656",
    "sha256_file": "zulu13.27.9-ca-jdk13-linux_i686.tar.gz.sha256",
    "sha512": "28f857aa5a0e4256496e7d61ae28395bb850de92b27300d44d93c10303a19f7537c9c4c61016abdfa4a1885beb311a1f31f0daf735a10cacf8efc37694ea5211",
    "sha512_file": "zulu13.27.9-ca-jdk13-linux_i686.tar.gz.sha512",
    "size": 198656514,
    "url": "https://static.azul.com/zulu/bin/zulu13.27.9-ca-jdk13-linux_i686.tar.gz",
    "vendor": "zulu",
    "version": "13.27.9"
  },
  {
    "architecture": "i686",
    "features": [],
    "file_type": "tar.gz",
    "filename": "zulu13.27.9-ca-jdk13.0.0-linux_i686.tar.gz",
    "image_type": "jdk",
    "java_version": "13.0.0",
    "jvm_impl": "hotspot",
    "md5": "51ea2aa32a871ed66931aedc0bc0065c",
    "md5_file": "zulu13.27.9-ca-jdk13.0.0-linux_i686.tar.gz.md5",
    "os": "linux",
    "release_type": "ga",
    "sha1": "68099c4724c531b0ad045a4ce68a2012f22bb9b3",
    "sha1_file": "zulu13.27.9-ca-jdk13.0.0-linux_i686.tar.gz.sha1",
    "sha256": "cf08df04c7e86e4f0547418ca8e162593e36784b11b811e9ccadd0801aa75656",
    "sha256_file": "zulu13.27.9-ca-jdk13.0.0-linux_i686.tar.gz.sha256",
    "sha512": "28f857aa5a0e4256496e7d61ae28395bb850de92b27300d44d93c10303a19f7537c9c4c61016abdfa4a1885beb311a1f31f0daf735a10cacf8efc37694ea5211",
    "sha512_file": "zulu13.27.9-ca-jdk13.0.0-linux_i686.tar.gz.sha512",
    "size": 198656514,
    "url": "https://static.azul.com/zulu/bin/zulu13.27.9-ca-jdk13.0.0-linux_i686.tar.gz",
    "vendor": "zulu",
    "version": "13.27.9"
  },
  {
    "architecture": "i686",
    "features": [],
    "file_type": "tar.gz",
    "filename": "zulu13.28.11-ca-jdk13.0.1-linux_i686.tar.gz",
    "image_type": "jdk",
    "java_version": "13.0.1",
    "jvm_impl": "hotspot",
    "md5": "2b337eecaa8c1f39258c061c0dad3821",
    "md5_file": "zulu13.28.11-ca-jdk13.0.1-linux_i686.tar.gz.md5",
    "os": "linux",
    "release_type": "ga",
    "sha1": "2c50726384fb97ccf0eb3921556bb39ec7491f61",
    "sha1_file": "zulu13.28.11-ca-jdk13.0.1-linux_i686.tar.gz.sha1",
    "sha256": "8c134b1efa452409fa3ebf6bcef4df6fd521c8b2a0d1d68da7d3ffdcb5ab0c79",
    "sha256_file": "zulu13.28.11-ca-jdk13.0.1-linux_i686.tar.gz.sha256",
    "sha512": "0582b4a8e58a74e0f203a4d4cc48605c6a93369773f96d5998a6add82b34e05a09766c4eecf232c7482d99d18096267bfa186e8df86ef3a997a6a43016b2391a",
    "sha512_file": "zulu13.28.11-ca-jdk13.0.1-linux_i686.tar.gz.sha512",
    "size": 201325805,
    "url": "https://static.azul.com/zulu/bin/zulu13.28.11-ca-jdk13.0.1-linux_i686.tar.gz",
    "vendor": "zulu",
    "version": "13.28.11"
  },
  {
    "architecture": "i686",
    "features": [],
    "file_type": "tar.gz",
    "filename": "zulu13.29.9-ca-jdk13.0.2-linux_i686.tar.gz",
    "image_type": "jdk",
    "java_version": "13.0.2",
    "jvm_impl": "hotspot",
    "md5": "baa694bf18e50c8ce9b79e6a6b067daf",
    "md5_file": "zulu13.29.9-ca-jdk13.0.2-linux_i686.tar.gz.md5",
    "os": "linux",
    "release_type": "ga",
    "sha1": "2b26f8ef58ba2bdcd34246a4f40c8f6f0ea88505",
    "sha1_file": "zulu13.29.9-ca-jdk13.0.2-linux_i686.tar.gz.sha1",
    "sha256": "5a8b226d672bfcc27c5f44aa5fc20ce3ec4d8478f97448f89628297c882430b1",
    "sha256_file": "zulu13.29.9-ca-jdk13.0.2-linux_i686.tar.gz.sha256",
    "sha512": "b9bc8d87ff425b7b29a48e7997bbc93bb7977697542fcc417863c699e915901da287e549650a94db77c9411271ef2d65c4499e363d8c185adf6fb52ef05771df",
    "sha512_file": "zulu13.29.9-ca-jdk13.0.2-linux_i686.tar.gz.sha512",
    "size": 198728479,
    "url": "https://static.azul.com/zulu/bin/zulu13.29.9-ca-jdk13.0.2-linux_i686.tar.gz",
    "vendor": "zulu",
    "version": "13.29.9"
  },
  {
    "architecture": "i686",
    "features": [],
    "file_type": "zip",
    "filename": "zulu13.29.9-ca-jdk13.0.2-linux_i686.zip",
    "image_type": "jdk",
    "java_version": "13.0.2",
    "jvm_impl": "hotspot",
    "md5": "e1969bbd43f6ca2100ae0685fc306e26",
    "md5_file": "zulu13.29.9-ca-jdk13.0.2-linux_i686.zip.md5",
    "os": "linux",
    "release_type": "ga",
    "sha1": "03258cc1a6e5e6c9bd632e96ebb179347f6567a5",
    "sha1_file": "zulu13.29.9-ca-jdk13.0.2-linux_i686.zip.sha1",
    "sha256": "b3c065ade6252dbf6cd52fee4f0f41a94c6b383b5db0789f9465279a67d55ff5",
    "sha256_file": "zulu13.29.9-ca-jdk13.0.2-linux_i686.zip.sha256",
    "sha512": "2cf5e417ee3561e14d5dad322df0506eeb2df9fcae5eb8f1df0dedcf66872b83225239815eb2a338d2bfdedcc83f83bf8042c8049fa39814375fff723e0a5836",
    "sha512_file": "zulu13.29.9-ca-jdk13.0.2-linux_i686.zip.sha512",
    "size": 202583823,
    "url": "https://static.azul.com/zulu/bin/zulu13.29.9-ca-jdk13.0.2-linux_i686.zip",
    "vendor": "zulu",
    "version": "13.29.9"
  },
  {
    "architecture": "i686",
    "features": [],
    "file_type": "tar.gz",
    "filename": "zulu13.31.11-ca-jdk13.0.3-linux_i686.tar.gz",
    "image_type": "jdk",
    "java_version": "13.0.3",
    "jvm_impl": "hotspot",
    "md5": "bc95f43b47d622d249985b614a73f931",
    "md5_file": "zulu13.31.11-ca-jdk13.0.3-linux_i686.tar.gz.md5",
    "os": "linux",
    "release_type": "ga",
    "sha1": "eae60a57bdb1c4ec1d30efaed22ee1ad5562bc6b",
    "sha1_file": "zulu13.31.11-ca-jdk13.0.3-linux_i686.tar.gz.sha1",
    "sha256": "fc3a7961391c8604994e373b4492e01612dfb00bf7104782ab8796033f876df4",
    "sha256_file": "zulu13.31.11-ca-jdk13.0.3-linux_i686.tar.gz.sha256",
    "sha512": "81f481acf7c92a545cb0915967a247cd4abbc7fad82eafdccc44c38f77af26abf6b96f3a2ae1d06f2a99652f2ca5d33d4d4a5eccc8db918cadd9a420eaa000cf",
    "sha512_file": "zulu13.31.11-ca-jdk13.0.3-linux_i686.tar.gz.sha512",
    "size": 198762593,
    "url": "https://static.azul.com/zulu/bin/zulu13.31.11-ca-jdk13.0.3-linux_i686.tar.gz",
    "vendor": "zulu",
    "version": "13.31.11"
  },
  {
    "architecture": "i686",
    "features": [],
    "file_type": "zip",
    "filename": "zulu13.31.11-ca-jdk13.0.3-linux_i686.zip",
    "image_type": "jdk",
    "java_version": "13.0.3",
    "jvm_impl": "hotspot",
    "md5": "6b3dea9dcba1c56fc84c98f7a24884fd",
    "md5_file": "zulu13.31.11-ca-jdk13.0.3-linux_i686.zip.md5",
    "os": "linux",
    "release_type": "ga",
    "sha1": "33eff8f3f3ae8d9867b069e1c41c1e1ec1a6927e",
    "sha1_file": "zulu13.31.11-ca-jdk13.0.3-linux_i686.zip.sha1",
    "sha256": "b15d9fe69ced16029263c1df81b4e50a06c3dba6ca101ee096010e749d8a3c65",
    "sha256_file": "zulu13.31.11-ca-jdk13.0.3-linux_i686.zip.sha256",
    "sha512": "19d28ac773fa6bb4134f3341a03cafd81f88fbf934e2043bc06c396fa3748e0a17d54453170745217d51bf772023760f4d237fed71d7be1f481c48d9724b49c8",
    "sha512_file": "zulu13.31.11-ca-jdk13.0.3-linux_i686.zip.sha512",
    "size": 202605496,
    "url": "https://static.azul.com/zulu/bin/zulu13.31.11-ca-jdk13.0.3-linux_i686.zip",
    "vendor": "zulu",
    "version": "13.31.11"
  },
  {
    "architecture": "i686",
    "features": [],
    "file_type": "tar.gz",
    "filename": "zulu13.33.25-ca-jdk13.0.4-linux_i686.tar.gz",
    "image_type": "jdk",
    "java_version": "13.0.4",
    "jvm_impl": "hotspot",
    "md5": "00c7db1db732cb0572643aaa00dd9e80",
    "md5_file": "zulu13.33.25-ca-jdk13.0.4-linux_i686.tar.gz.md5",
    "os": "linux",
    "release_type": "ga",
    "sha1": "f0667de232fc2b46eaa4fd4a612a98d8b4df7b0b",
    "sha1_file": "zulu13.33.25-ca-jdk13.0.4-linux_i686.tar.gz.sha1",
    "sha256": "f16048df91a09ed6c039cf994de4af490445bf06580197fa746d583145baa4a2",
    "sha256_file": "zulu13.33.25-ca-jdk13.0.4-linux_i686.tar.gz.sha256",
    "sha512": "1dedede42f2b9888956ed42cdac1de681e5351739beada4f2ff888352def2dbf13f7d5324f3a515547a39132fddbfc1e26e7a286f3caf5df1b93dd2413cfb7c2",
    "sha512_file": "zulu13.33.25-ca-jdk13.0.4-linux_i686.tar.gz.sha512",
    "size": 198907382,
    "url": "https://static.azul.com/zulu/bin/zulu13.33.25-ca-jdk13.0.4-linux_i686.tar.gz",
    "vendor": "zulu",
    "version": "13.33.25"
  },
  {
    "architecture": "i686",
    "features": [],
    "file_type": "zip",
    "filename": "zulu13.33.25-ca-jdk13.0.4-linux_i686.zip",
    "image_type": "jdk",
    "java_version": "13.0.4",
    "jvm_impl": "hotspot",
    "md5": "83e283945c0cff2f5637a44a6649aeac",
    "md5_file": "zulu13.33.25-ca-jdk13.0.4-linux_i686.zip.md5",
    "os": "linux",
    "release_type": "ga",
    "sha1": "121dac07f3b7c5662f3ee2be512bffe1fcee27c3",
    "sha1_file": "zulu13.33.25-ca-jdk13.0.4-linux_i686.zip.sha1",
    "sha256": "505ceeae1c73f9a59c91eb33f525d0e36204d82b596a8ca5e550278835a269c4",
    "sha256_file": "zulu13.33.25-ca-jdk13.0.4-linux_i686.zip.sha256",
    "sha512": "2929194a12221521dca5ebde9e4378d12439812a0691fceb6981bdac6bda74afa8fac7d749f982adf83bd6daaf66dac249aed2ec7152924aaeeb038587de549c",
    "sha512_file": "zulu13.33.25-ca-jdk13.0.4-linux_i686.zip.sha512",
    "size": 202768045,
    "url": "https://static.azul.com/zulu/bin/zulu13.33.25-ca-jdk13.0.4-linux_i686.zip",
    "vendor": "zulu",
    "version": "13.33.25"
  },
  {
    "architecture": "i686",
    "features": [],
    "file_type": "tar.gz",
    "filename": "zulu13.35.17-ca-jdk13.0.5-linux_i686.tar.gz",
    "image_type": "jdk",
    "java_version": "13.0.5",
    "jvm_impl": "hotspot",
    "md5": "a6da994179e38ef130af98d3ca025f9f",
    "md5_file": "zulu13.35.17-ca-jdk13.0.5-linux_i686.tar.gz.md5",
    "os": "linux",
    "release_type": "ga",
    "sha1": "7464d531e8ed7e942fbdd262447ca35a19cb9a9e",
    "sha1_file": "zulu13.35.17-ca-jdk13.0.5-linux_i686.tar.gz.sha1",
    "sha256": "1b291e24eea6a7de53b260006e94247864c05290c6c048fa51cf9a4751afcb75",
    "sha256_file": "zulu13.35.17-ca-jdk13.0.5-linux_i686.tar.gz.sha256",
    "sha512": "00e8daeb2d53e80b41816c3ebe16a6614bb0c009020f1d01a39fb216390a9286055a5fa9db3ef0bf0399367a87d87743cd19ff33605944d6b5438970d015a25d",
    "sha512_file": "zulu13.35.17-ca-jdk13.0.5-linux_i686.tar.gz.sha512",
    "size": 198926372,
    "url": "https://static.azul.com/zulu/bin/zulu13.35.17-ca-jdk13.0.5-linux_i686.tar.gz",
    "vendor": "zulu",
    "version": "13.35.17"
  },
  {
    "architecture": "i686",
    "features": [],
    "file_type": "zip",
    "filename": "zulu13.35.17-ca-jdk13.0.5-linux_i686.zip",
    "image_type": "jdk",
    "java_version": "13.0.5",
    "jvm_impl": "hotspot",
    "md5": "7c89867866af241ede8ff1d6de5bfe4e",
    "md5_file": "zulu13.35.17-ca-jdk13.0.5-linux_i686.zip.md5",
    "os": "linux",
    "release_type": "ga",
    "sha1": "859698620d09278402813eccc190adc14ebcf248",
    "sha1_file": "zulu13.35.17-ca-jdk13.0.5-linux_i686.zip.sha1",
    "sha256": "983b6757fcf3d131dbcb10c1de852bb1697c8c6b18e13a065fb2d1a169f48eda",
    "sha256_file": "zulu13.35.17-ca-jdk13.0.5-linux_i686.zip.sha256",
    "sha512": "783e27cdcef590fe1cc8359a59bbbe8ab690a037ce3e7c3b0854af415c734fa6261e0b5b8b45b438daa648bca43123f6356b714eae34d1e9550513d2c41e0929",
    "sha512_file": "zulu13.35.17-ca-jdk13.0.5-linux_i686.zip.sha512",
    "size": 202788264,
    "url": "https://static.azul.com/zulu/bin/zulu13.35.17-ca-jdk13.0.5-linux_i686.zip",
    "vendor": "zulu",
    "version": "13.35.17"
  },
  {
    "architecture": "i686",
    "features": [],
    "file_type": "tar.gz",
    "filename": "zulu13.35.51-ca-jdk13.0.5.1-linux_i686.tar.gz",
    "image_type": "jdk",
    "java_version": "13.0.5.1",
    "jvm_impl": "hotspot",
    "md5": "483bdb419301b19297137a25a30c10bd",
    "md5_file": "zulu13.35.51-ca-jdk13.0.5.1-linux_i686.tar.gz.md5",
    "os": "linux",
    "release_type": "ga",
    "sha1": "fb1cd1bf355ec1663ae0385b0a4c87e93057989f",
    "sha1_file": "zulu13.35.51-ca-jdk13.0.5.1-linux_i686.tar.gz.sha1",
    "sha256": "3423496b586e9771ba71463448ae57822d5a27b5d68c90b6be964915e36d8dd0",
    "sha256_file": "zulu13.35.51-ca-jdk13.0.5.1-linux_i686.tar.gz.sha256",
    "sha512": "32e013ecadff6c144cf46e3dc64e85ac8bf992f6a49e4c5498d545a8a566b29b3bf967142abb4cc96c09927850d05183133cbe212b54e1e0c4d0d5c16d6220b1",
    "sha512_file": "zulu13.35.51-ca-jdk13.0.5.1-linux_i686.tar.gz.sha512",
    "size": 198925698,
    "url": "https://static.azul.com/zulu/bin/zulu13.35.51-ca-jdk13.0.5.1-linux_i686.tar.gz",
    "vendor": "zulu",
    "version": "13.35.51"
  },
  {
    "architecture": "i686",
    "features": [],
    "file_type": "zip",
    "filename": "zulu13.35.51-ca-jdk13.0.5.1-linux_i686.zip",
    "image_type": "jdk",
    "java_version": "13.0.5.1",
    "jvm_impl": "hotspot",
    "md5": "6cef21e1fa221887ccf28bfe83ba2f79",
    "md5_file": "zulu13.35.51-ca-jdk13.0.5.1-linux_i686.zip.md5",
    "os": "linux",
    "release_type": "ga",
    "sha1": "c2864c4ac05cafb8d47ec85c56b134873f9770ed",
    "sha1_file": "zulu13.35.51-ca-jdk13.0.5.1-linux_i686.zip.sha1",
    "sha256": "a6055939068cfc40b3e1b03ba5d75eaa3f934786ebea03a782940e012ed5d309",
    "sha256_file": "zulu13.35.51-ca-jdk13.0.5.1-linux_i686.zip.sha256",
    "sha512": "f79c9611b22959f73474973b10cfea9730a789f499d7cea3000984b03bab6fb165556298d0da125339f34ee32bf2212d3967e9f63846338a468240ff637f4013",
    "sha512_file": "zulu13.35.51-ca-jdk13.0.5.1-linux_i686.zip.sha512",
    "size": 202792357,
    "url": "https://static.azul.com/zulu/bin/zulu13.35.51-ca-jdk13.0.5.1-linux_i686.zip",
    "vendor": "zulu",
    "version": "13.35.51"
  },
  {
    "architecture": "i686",
    "features": [],
    "file_type": "tar.gz",
    "filename": "zulu13.37.21-ca-jdk13.0.6-linux_i686.tar.gz",
    "image_type": "jdk",
    "java_version": "13.0.6",
    "jvm_impl": "hotspot",
    "md5": "911fe72964aae46e05f0535f089f2e1e",
    "md5_file": "zulu13.37.21-ca-jdk13.0.6-linux_i686.tar.gz.md5",
    "os": "linux",
    "release_type": "ga",
    "sha1": "71174f3c7144f5565f9ee206f1d2c85fcc9d4b24",
    "sha1_file": "zulu13.37.21-ca-jdk13.0.6-linux_i686.tar.gz.sha1",
    "sha256": "864b89c76fa1f7224eeaf398c4d2c270730b71eccdcf21f0e5e47257cebbd3fa",
    "sha256_file": "zulu13.37.21-ca-jdk13.0.6-linux_i686.tar.gz.sha256",
    "sha512": "894bb68d1e871941a40abf08ac193c6badd1ea3a369f34598f61ff4dba8616c7c6a50c662e75f6c0b6c2b6a28dad479db92acb651ebb0baad9202c0b0bbefdaa",
    "sha512_file": "zulu13.37.21-ca-jdk13.0.6-linux_i686.tar.gz.sha512",
    "size": 198962547,
    "url": "https://static.azul.com/zulu/bin/zulu13.37.21-ca-jdk13.0.6-linux_i686.tar.gz",
    "vendor": "zulu",
    "version": "13.37.21"
  },
  {
    "architecture": "i686",
    "features": [],
    "file_type": "zip",
    "filename": "zulu13.37.21-ca-jdk13.0.6-linux_i686.zip",
    "image_type": "jdk",
    "java_version": "13.0.6",
    "jvm_impl": "hotspot",
    "md5": "1fc51060a2c12254907f3243ef87f14f",
    "md5_file": "zulu13.37.21-ca-jdk13.0.6-linux_i686.zip.md5",
    "os": "linux",
    "release_type": "ga",
    "sha1": "0ab1ff954ef472c320fcf27753414f1844158fac",
    "sha1_file": "zulu13.37.21-ca-jdk13.0.6-linux_i686.zip.sha1",
    "sha256": "efbaebeab351bf69b2d6111201a3cfe12c0d11b931c0663eae56163334e3f372",
    "sha256_file": "zulu13.37.21-ca-jdk13.0.6-linux_i686.zip.sha256",
    "sha512": "3003a6dbf7551cf028cef002fa81579f1887eaa0e35371d8233b915428a37d5f839ca02445bd90e52343109a061c9625b436c601517c5ca3b9d1db7fb29065e7",
    "sha512_file": "zulu13.37.21-ca-jdk13.0.6-linux_i686.zip.sha512",
    "size": 202835604,
    "url": "https://static.azul.com/zulu/bin/zulu13.37.21-ca-jdk13.0.6-linux_i686.zip",
    "vendor": "zulu",
    "version": "13.37.21"
  },
  {
    "architecture": "i686",
    "features": [],
    "file_type": "tar.gz",
    "filename": "zulu13.40.15-ca-jdk13.0.7-linux_i686.tar.gz",
    "image_type": "jdk",
    "java_version": "13.0.7",
    "jvm_impl": "hotspot",
    "md5": "c56d4865b3475cffc4d34a8a0266cc8f",
    "md5_file": "zulu13.40.15-ca-jdk13.0.7-linux_i686.tar.gz.md5",
    "os": "linux",
    "release_type": "ga",
    "sha1": "d95a3c160396eb26b80afc06e0c4483bb8a7e9eb",
    "sha1_file": "zulu13.40.15-ca-jdk13.0.7-linux_i686.tar.gz.sha1",
    "sha256": "380ac13ad6dc30fbff62eac7ccb5d9cb006d13045bd3fd4e84cd2930f3a1790d",
    "sha256_file": "zulu13.40.15-ca-jdk13.0.7-linux_i686.tar.gz.sha256",
    "sha512": "9f65dec3b5482cb7bebf6bca4d98cc15dac832d458f12534c0c5385400bcfd2d750a7b0716cdfd8a3d26c5eb506f83131f3b3b9f8e5a3f4916fa8e6326d3f91a",
    "sha512_file": "zulu13.40.15-ca-jdk13.0.7-linux_i686.tar.gz.sha512",
    "size": 199006127,
    "url": "https://static.azul.com/zulu/bin/zulu13.40.15-ca-jdk13.0.7-linux_i686.tar.gz",
    "vendor": "zulu",
    "version": "13.40.15"
  },
  {
    "architecture": "i686",
    "features": [],
    "file_type": "zip",
    "filename": "zulu13.40.15-ca-jdk13.0.7-linux_i686.zip",
    "image_type": "jdk",
    "java_version": "13.0.7",
    "jvm_impl": "hotspot",
    "md5": "078d2bb2acd7f52e16c36724c91281d0",
    "md5_file": "zulu13.40.15-ca-jdk13.0.7-linux_i686.zip.md5",
    "os": "linux",
    "release_type": "ga",
    "sha1": "e2b8d5275db6517ffb5b495e2bcc191f10a3ff0e",
    "sha1_file": "zulu13.40.15-ca-jdk13.0.7-linux_i686.zip.sha1",
    "sha256": "53de9fb9d745cf6387ba0d5f783c0d0454ab9220e77c872f762bc49ba939262d",
    "sha256_file": "zulu13.40.15-ca-jdk13.0.7-linux_i686.zip.sha256",
    "sha512": "e94cd70624a4a061f2693c7c11999159667723073f00f966cac7f90c104328b488a0fd0fec1e0aa20fd7debde2f0bde6d5a15315f5b779db5db3e0f2630516d4",
    "sha512_file": "zulu13.40.15-ca-jdk13.0.7-linux_i686.zip.sha512",
    "size": 202896586,
    "url": "https://static.azul.com/zulu/bin/zulu13.40.15-ca-jdk13.0.7-linux_i686.zip",
    "vendor": "zulu",
    "version": "13.40.15"
  }
]
